mongoquery/__init__.py
mongo_query_match-2.0.0.dist-info/METADATA
mongo_query_match-2.0.0.dist-info/WHEEL
mongo_query_match-2.0.0.dist-info/licenses/LICENSE
mongo_query_match-2.0.0.dist-info/RECORD
