Metadata-Version: 2.4
Name: mongo-query-match
Version: 2.0.0
Summary: A utility library that provides a MongoDB-like query language for querying python collections. It's mainly intended to parse objects structured as fundamental types in a similar fashion to what is produced by JSON or YAML parsers.
Author-email: Olivier Carrere <olivier.carrere@gmail.com>, Reuben Morais <reuben.morais@gmail.com>
License-File: LICENSE
Keywords: match,mongodb,query
Classifier: Development Status :: 5 - Production/Stable
Classifier: Programming Language :: Python
Classifier: Programming Language :: Python :: 3
Classifier: Topic :: Utilities
Requires-Python: <4,>=3.9
